Workbook

Sheet PRESUPUESTO DE VENTAS
C3: PRESUPUESTO DE VENTAS
C5: Realice el presupuesto de ventas, a continuación los datos:
C7: VENTAS
C8: Marzo | D8: 40000 | F8: Ventas crédito | G8: 0.4
C9: Abril | D9: 50000 | F9: Ventas contado | G9: 0.6
C10: Mayo | D10: 80000
C11: Junio | D11: 60000
C12: Julio | D12: 50000
C14: Los cobros se toman el porcentaje de contado del mes actual y se suma la ventas de crédito del mes anterior.
C17: Presupuesto de Compras
G19: Marzo | I19: Abril | K19: Mayo | M19: Junio | O19: Julio | Q19: Abril - Julio
C20: Ventas de crédito 40% | G20: =+D8*0.4 -> 16000 | I20: =+D9*0.4 -> 20000 | K20: =+D10*0.4 -> 32000 | M20: =+D11*0.4 -> 24000 | O20: =+D12*0.4 -> 20000
C21: más: ventas de efectivo/ contado, 60% | G21: =+D8*0.6 -> 24000 | I21: =+D9*0.6 -> 30000 | K21: =+D10*0.6 -> 48000 | M21: =+D11*0.6 -> 36000 | O21: =+D12*0.6 -> 30000
C22: Ventas totales | G22: =SUM(G20:G21) -> 40000 | I22: =SUM(I20:I21) -> 50000 | K22: =SUM(K20:K21) -> 80000 | M22: =SUM(M20:M21) -> 60000 | O22: =SUM(O20:O21) -> 50000 | Q22: =SUM(I22:O22) -> 240000
C24: Cobros en efectivo (contado)
C25: Ventas en efectivo este mes | I25: =+I21 -> 30000 | K25: =+K21 -> 48000 | M25: =+M21 -> 36000 | O25: =+O21 -> 30000
C26: más 100% de las ventas a crédito del mes pasado | I26: =+G20 -> 16000 | K26: =+I20 -> 20000 | M26: =+K20 -> 32000 | O26: =+M20 -> 24000
C27: Cobros totales | I27: =SUM(I25:I26) -> 46000 | K27: =SUM(K25:K26) -> 68000 | M27: =SUM(M25:M26) -> 68000 | O27: =SUM(O25:O26) -> 54000 | Q27: =SUM(I27:O27) -> 236000

Sheet Plan de Ventas y gastos 2023
C2: PROYECCIÓN DE VENTAS
E4: 44927 | F4: 44958 | G4: 44986 | H4: 45017 | I4: 45047 | J4: 45078 | K4: 45108 | L4: 45139 | M4: 45170 | N4: 45200 | O4: 45231 | P4: 45261
D5: Estacionalidad | E5: 0.12 | F5: 0.1 | G5: 0.08 | H5: 0.06 | I5: 0.06 | J5: 0.05 | K5: 0.04 | L5: 0.03 | M5: 0.08 | N5: 0.1 | O5: 0.12 | P5: 0.16 | Q5: =SUM(E5:P5) -> 1
D6: PLAN DE VENTAS
E7: 44927 | F7: 44958 | G7: 44986 | H7: 45017 | I7: 45047 | J7: 45078 | K7: 45108 | L7: 45139 | M7: 45170 | N7: 45200 | O7: 45231 | P7: 45261
D8: Ventas 2023 | E8: =+$D$9*E5 -> 30747.12 | F8: =+$D$9*F5 -> 25622.6 | G8: =+$D$9*G5 -> 20498.08 | H8: =+$D$9*H5 -> 15373.56 | I8: =+$D$9*I5 -> 15373.56 | J8: =+$D$9*J5 -> 12811.3 | K8: =+$D$9*K5 -> 10249.04 | L8: =+$D$9*L5 -> 7686.78 | ... P8: =+$D$9*P5 -> 40996.16 | Q8: =SUM(E8:P8) -> 256226
C9: Total | D9: 256226
C10: 0 | D10: Ventas modificadas | Q10: =SUM(E10:P10) -> 0
D11: =+'[1]Capital de Trabajo'!A14 -> 0
C13: 0.15 | D13: Ventas de Contado | E13: =+$C$13*E8 -> 4612.068 | F13: =+$C$13*F8 -> 3843.39 | G13: =+$C$13*G8 -> 3074.712 | H13: =+$C$13*H8 -> 2306.034 | I13: =+$C$13*I8 -> 2306.034 | J13: =+$C$13*J8 -> 1921.695 | K13: =+$C$13*K8 -> 1537.356 | L13: =+$C$13*L8 -> 1153.017 | ... P13: =+$C$13*P8 -> 6149.424 | Q13: =SUM(E13:P13) -> 38433.9
C14: 0.85 | D14: Ventas de Crédito | E14: =+$C$14*E8 -> 26135.052 | F14: =+$C$14*F8 -> 21779.21 | G14: =+$C$14*G8 -> 17423.368 | H14: =+$C$14*H8 -> 13067.526 | I14: =+$C$14*I8 -> 13067.526 | J14: =+$C$14*J8 -> 10889.605 | K14: =+$C$14*K8 -> 8711.684 | L14: =+$C$14*L8 -> 6533.763 | ... P14: =+$C$14*P8 -> 34846.736 | Q14: =SUM(E14:P14) -> 217792.1
Q15: =SUM(Q13:Q14) -> 256226
D16: Costo ventas
D17: 0.55 | E17: =+$D$17*E8 -> 16910.916 | F17: =+$D$17*F8 -> 14092.43 | G17: =+$D$17*G8 -> 11273.944 | H17: =+$D$17*H8 -> 8455.458 | I17: =+$D$17*I8 -> 8455.458 | J17: =+$D$17*J8 -> 7046.215 | K17: =+$D$17*K8 -> 5636.972 | L17: =+$D$17*L8 -> 4227.729 | ... P17: =+$D$17*P8 -> 22547.888 | Q17: =SUM(E17:P17) -> 140924.3
D18: Diferencia es el margen 45% | E18: =+E8-E17 -> 13836.204 | F18: =+F8-F17 -> 11530.17 | G18: =+G8-G17 -> 9224.136 | H18: =+H8-H17 -> 6918.102 | I18: =+I8-I17 -> 6918.102 | J18: =+J8-J17 -> 5765.085 | K18: =+K8-K17 -> 4612.068 | L18: =+L8-L17 -> 3459.051 | ... P18: =+P8-P17 -> 18448.272 | Q18: =SUM(E18:P18) -> 115301.7
Q19: =SUM(Q17:Q18) -> 256226
D20: Margen de Ganancia
D21: =100%-D17 -> 0.45 | E21: =+$D$21*E8 -> 13836.204 | F21: =+$D$21*F8 -> 11530.17 | G21: =+$D$21*G8 -> 9224.136 | H21: =+$D$21*H8 -> 6918.102 | I21: =+$D$21*I8 -> 6918.102 | J21: =+$D$21*J8 -> 5765.085 | K21: =+$D$21*K8 -> 4612.068 | L21: =+$D$21*L8 -> 3459.051 | ... P21: =+$D$21*P8 -> 18448.272 | Q21: =SUM(E21:P21) -> 115301.7
D24: PLAN DE GASTOS
B25: GASTOS TOTALES OPERATIVOS FINANCIEROS
B26: OBJETIVOS DE GASTO 2023
B27: GASTO OPERATIVO | C27: 2022
B28: GASTO OPERATIVO | C28: 2023 | D28: =SUM(D29:D31) -> 72694 | E28: 0.9 | F28: REDUCCIÓN DEL 10% RESPECTO AL 2022
B29: GASTO DE VENTAS | C29: 2023 | D29: 29018 | E29: =+'[1]Base de Datos'!E28 -> 0.4 | F29: DEL GASTO OPERATIVO 2023
B30: GASTO ADMINISTRATIVO | C30: 2023 | D30: 38051 | E30: POR AJUSTE
B31: GASTO DEPRECIACIÓN | C31: 2023 | D31: 5625 | E31: IGUAL A AÑOS ANTERIORES
B33: GASTO FINANCIERO | C33: 2023 | D33: 5085 | E33: SEGÚN PLAN DE DEUDA
E35: =+E7 -> 44927 | F35: =+F7 -> 44958 | G35: =+G7 -> 44986 | H35: =+H7 -> 45017 | I35: =+I7 -> 45047 | J35: =+J7 -> 45078 | K35: =+K7 -> 45108 | L35: =+L7 -> 45139 | ... P35: =+P7 -> 45261
D36: =+[1]Resultados!C8 -> Gastos Operativos
D37: =+[1]Resultados!C9 -> Gasto Ventas | E37: =+$D$29*E5 -> 3482.16 | F37: =+$D$29*F5 -> 2901.8 | G37: =+$D$29*G5 -> 2321.44 | H37: =+$D$29*H5 -> 1741.08 | I37: =+$D$29*I5 -> 1741.08 | J37: =+$D$29*J5 -> 1450.9 | K37: =+$D$29*K5 -> 1160.72 | L37: =+$D$29*L5 -> 870.54 | ... P37: =+$D$29*P5 -> 4642.88 | Q37: =SUM(E37:P37) -> 29018
D38: =+[1]Resultados!C10 -> Gasto Administrativo | E38: =+$D$30*E5 -> 4566.12 | F38: =+$D$30*F5 -> 3805.1 | G38: =+$D$30*G5 -> 3044.08 | H38: =+$D$30*H5 -> 2283.06 | I38: =+$D$30*I5 -> 2283.06 | J38: =+$D$30*J5 -> 1902.55 | K38: =+$D$30*K5 -> 1522.04 | L38: =+$D$30*L5 -> 1141.53 | ... P38: =+$D$30*P5 -> 6088.16 | Q38: =SUM(E38:P38) -> 38051
D39: =+[1]Resultados!C11 -> Depreciaciones | E39: =+$D$31/12 -> 468.75 | F39: =+$D$31/12 -> 468.75 | G39: =+$D$31/12 -> 468.75 | H39: =+$D$31/12 -> 468.75 | I39: =+$D$31/12 -> 468.75 | J39: =+$D$31/12 -> 468.75 | K39: =+$D$31/12 -> 468.75 | L39: =+$D$31/12 -> 468.75 | ... P39: =+$D$31/12 -> 468.75 | Q39: =SUM(E39:P39) -> 5625
D40: =+[1]Resultados!C12 -> Total Gasto Operativo | E40: =SUM(E37:E39) -> 8517.03 | F40: =SUM(F37:F39) -> 7175.65 | G40: =SUM(G37:G39) -> 5834.27 | H40: =SUM(H37:H39) -> 4492.89 | I40: =SUM(I37:I39) -> 4492.89 | J40: =SUM(J37:J39) -> 3822.2 | K40: =SUM(K37:K39) -> 3151.51 | L40: =SUM(L37:L39) -> 2480.82 | ... P40: =SUM(P37:P39) -> 11199.79 | Q40: =SUM(E40:P40) -> 72694
D41: Gasto Financiero | E41: =+$D$33/12 -> 423.75 | F41: =+$D$33/12 -> 423.75 | G41: =+$D$33/12 -> 423.75 | H41: =+$D$33/12 -> 423.75 | I41: =+$D$33/12 -> 423.75 | J41: =+$D$33/12 -> 423.75 | K41: =+$D$33/12 -> 423.75 | L41: =+$D$33/12 -> 423.75 | ... P41: =+$D$33/12 -> 423.75 | Q41: =SUM(E41:P41) -> 5085
D43: Gasto Financiero | E43: 427.93968 | F43: 427.19624 | G43: 426.44536 | H43: 425.68698 | I43: 424.92102 | J43: 424.14739 | K43: 423.36603 | L43: 422.57685 | M43: 421.77979 | N43: 420.97475 | O43: 420.16166 | P43: 419.34044 | Q43: =SUM(E43:P43) -> 5084.5362

Sheet Resultados proyectados 2023
C2: ESTADOS RESULTADOS PROYECTADOS 2023
D3: =+'[1]Plan de Ventas Y gastos'!E3 -> 44927 | E3: =+'[1]Plan de Ventas Y gastos'!F3 -> 44958 | F3: =+'[1]Plan de Ventas Y gastos'!G3 -> 44986 | G3: =+'[1]Plan de Ventas Y gastos'!H3 -> 45017 | H3: =+'[1]Plan de Ventas Y gastos'!I3 -> 45047 | I3: =+'[1]Plan de Ventas Y gastos'!J3 -> 45078 | J3: =+'[1]Plan de Ventas Y gastos'!K3 -> 45108 | K3: =+'[1]Plan de Ventas Y gastos'!L3 -> 45139 | ... O3: =+'[1]Plan de Ventas Y gastos'!P3 -> 45261 | P3: TOTAL
C4: Ventas | D4: =+'Plan de Ventas y gastos 2023'!E8 -> 30747.12 | E4: =+'Plan de Ventas y gastos 2023'!F8 -> 25622.6 | F4: =+'Plan de Ventas y gastos 2023'!G8 -> 20498.08 | G4: =+'Plan de Ventas y gastos 2023'!H8 -> 15373.56 | H4: =+'Plan de Ventas y gastos 2023'!I8 -> 15373.56 | I4: =+'Plan de Ventas y gastos 2023'!J8 -> 12811.3 | J4: =+'Plan de Ventas y gastos 2023'!K8 -> 10249.04 | K4: =+'Plan de Ventas y gastos 2023'!L8 -> 7686.78 | ... O4: =+'Plan de Ventas y gastos 2023'!P8 -> 40996.16 | P4: =SUM(D4:O4) -> 256226
C5: Costo ventas | D5: =+'Plan de Ventas y gastos 2023'!E17 -> 16910.916 | E5: =+'Plan de Ventas y gastos 2023'!F17 -> 14092.43 | F5: =+'Plan de Ventas y gastos 2023'!G17 -> 11273.944 | G5: =+'Plan de Ventas y gastos 2023'!H17 -> 8455.458 | H5: =+'Plan de Ventas y gastos 2023'!I17 -> 8455.458 | I5: =+'Plan de Ventas y gastos 2023'!J17 -> 7046.215 | J5: =+'Plan de Ventas y gastos 2023'!K17 -> 5636.972 | K5: =+'Plan de Ventas y gastos 2023'!L17 -> 4227.729 | ... O5: =+'Plan de Ventas y gastos 2023'!P17 -> 22547.888 | P5: =SUM(D5:O5) -> 140924.3
C6: Margen de Ganancia | D6: =+'Plan de Ventas y gastos 2023'!E21 -> 13836.204 | E6: =+'Plan de Ventas y gastos 2023'!F21 -> 11530.17 | F6: =+'Plan de Ventas y gastos 2023'!G21 -> 9224.136 | G6: =+'Plan de Ventas y gastos 2023'!H21 -> 6918.102 | H6: =+'Plan de Ventas y gastos 2023'!I21 -> 6918.102 | I6: =+'Plan de Ventas y gastos 2023'!J21 -> 5765.085 | J6: =+'Plan de Ventas y gastos 2023'!K21 -> 4612.068 | K6: =+'Plan de Ventas y gastos 2023'!L21 -> 3459.051 | ... O6: =+'Plan de Ventas y gastos 2023'!P21 -> 18448.272 | P6: =SUM(D6:O6) -> 115301.7 | Q6: =+P5+P6 -> 256226
C7: Margen de Ganancia % | D7: 0.45 | E7: 0.45 | F7: 0.45 | G7: 0.45 | H7: 0.45 | I7: 0.45 | J7: 0.45 | K7: 0.45 | L7: 0.45 | M7: 0.45 | N7: 0.45 | O7: 0.45
B9: 1 | C9: =+[1]Resultados!C8 -> Gastos Operativos | Q9: CONTROL
B10: a | C10: =+[1]Resultados!C9 -> Gasto Ventas | D10: =+'Plan de Ventas y gastos 2023'!E37 -> 3482.16 | E10: =+'Plan de Ventas y gastos 2023'!F37 -> 2901.8 | F10: =+'Plan de Ventas y gastos 2023'!G37 -> 2321.44 | G10: =+'Plan de Ventas y gastos 2023'!H37 -> 1741.08 | H10: =+'Plan de Ventas y gastos 2023'!I37 -> 1741.08 | I10: =+'Plan de Ventas y gastos 2023'!J37 -> 1450.9 | J10: =+'Plan de Ventas y gastos 2023'!K37 -> 1160.72 | K10: =+'Plan de Ventas y gastos 2023'!L37 -> 870.54 | ... O10: =+'Plan de Ventas y gastos 2023'!P37 -> 4642.88 | P10: =SUM(D10:O10) -> 29018 | Q10: =+'Plan de Ventas y gastos 2023'!D29 -> 29018
B11: b | C11: =+[1]Resultados!C10 -> Gasto Administrativo | D11: =+'Plan de Ventas y gastos 2023'!E38 -> 4566.12 | E11: =+'Plan de Ventas y gastos 2023'!F38 -> 3805.1 | F11: =+'Plan de Ventas y gastos 2023'!G38 -> 3044.08 | G11: =+'Plan de Ventas y gastos 2023'!H38 -> 2283.06 | H11: =+'Plan de Ventas y gastos 2023'!I38 -> 2283.06 | I11: =+'Plan de Ventas y gastos 2023'!J38 -> 1902.55 | J11: =+'Plan de Ventas y gastos 2023'!K38 -> 1522.04 | K11: =+'Plan de Ventas y gastos 2023'!L38 -> 1141.53 | ... O11: =+'Plan de Ventas y gastos 2023'!P38 -> 6088.16 | P11: =SUM(D11:O11) -> 38051 | Q11: =+'Plan de Ventas y gastos 2023'!D30 -> 38051
B12: c | C12: =+[1]Resultados!C11 -> Depreciaciones | D12: =+'Plan de Ventas y gastos 2023'!E39 -> 468.75 | E12: =+'Plan de Ventas y gastos 2023'!F39 -> 468.75 | F12: =+'Plan de Ventas y gastos 2023'!G39 -> 468.75 | G12: =+'Plan de Ventas y gastos 2023'!H39 -> 468.75 | H12: =+'Plan de Ventas y gastos 2023'!I39 -> 468.75 | I12: =+'Plan de Ventas y gastos 2023'!J39 -> 468.75 | J12: =+'Plan de Ventas y gastos 2023'!K39 -> 468.75 | K12: =+'Plan de Ventas y gastos 2023'!L39 -> 468.75 | ... O12: =+'Plan de Ventas y gastos 2023'!P39 -> 468.75 | P12: =SUM(D12:O12) -> 5625 | Q12: =+'Plan de Ventas y gastos 2023'!D31 -> 5625
C13: =+[1]Resultados!C12 -> Total Gasto Operativo | D13: =SUM(D10:D12) -> 8517.03 | E13: =SUM(E10:E12) -> 7175.65 | F13: =SUM(F10:F12) -> 5834.27 | G13: =SUM(G10:G12) -> 4492.89 | H13: =SUM(H10:H12) -> 4492.89 | I13: =SUM(I10:I12) -> 3822.2 | J13: =SUM(J10:J12) -> 3151.51 | K13: =SUM(K10:K12) -> 2480.82 | ... P13: =SUM(P10:P12) -> 72694 | Q13: =+'Plan de Ventas y gastos 2023'!D28 -> 72694
B14: UAII | C14: =+[1]Resultados!C13 -> Utlidades Operativas | D14: =+D6-D13 -> 5319.174 | E14: =+E6-E13 -> 4354.52 | F14: =+F6-F13 -> 3389.866 | G14: =+G6-G13 -> 2425.212 | H14: =+H6-H13 -> 2425.212 | I14: =+I6-I13 -> 1942.885 | J14: =+J6-J13 -> 1460.558 | K14: =+K6-K13 -> 978.231 | ... O14: =+O6-O13 -> 7248.482
B15: 2 | C15: =+[1]Resultados!C14 -> Gasto Financiero | D15: =+'Plan de Ventas y gastos 2023'!E41 -> 423.75 | E15: =+'Plan de Ventas y gastos 2023'!F41 -> 423.75 | F15: =+'Plan de Ventas y gastos 2023'!G41 -> 423.75 | G15: =+'Plan de Ventas y gastos 2023'!H41 -> 423.75 | H15: =+'Plan de Ventas y gastos 2023'!I41 -> 423.75 | I15: =+'Plan de Ventas y gastos 2023'!J41 -> 423.75 | J15: =+'Plan de Ventas y gastos 2023'!K41 -> 423.75 | K15: =+'Plan de Ventas y gastos 2023'!L41 -> 423.75 | ... O15: =+'Plan de Ventas y gastos 2023'!P41 -> 423.75 | P15: =SUM(D15:O15) -> 5085 | Q15: =+'Plan de Ventas y gastos 2023'!D33 -> 5085
B16: UAII | C16: =+[1]Resultados!C15 -> Utilidad antes de Impuestos | D16: =+D14-D15 -> 4895.424 | E16: =+E14-E15 -> 3930.77 | F16: =+F14-F15 -> 2966.116 | G16: =+G14-G15 -> 2001.462 | H16: =+H14-H15 -> 2001.462 | I16: =+I14-I15 -> 1519.135 | J16: =+J14-J15 -> 1036.808 | K16: =+K14-K15 -> 554.481 | ... O16: =+O14-O15 -> 6824.732 | P16: =SUM(D16:O16) -> 37522.7
B17: 0.3 | C17: =+[1]Resultados!C16 -> Impuestos Renta | D17: =+$B$17*D16 -> 1468.6272 | E17: =+$B$17*E16 -> 1179.231 | F17: =+$B$17*F16 -> 889.8348 | G17: =+$B$17*G16 -> 600.4386 | H17: =+$B$17*H16 -> 600.4386 | I17: =+$B$17*I16 -> 455.7405 | J17: =+$B$17*J16 -> 311.0424 | K17: =+$B$17*K16 -> 166.3443 | ... O17: =+$B$17*O16 -> 2047.4196 | P17: =SUM(D17:O17) -> 11256.81
C18: =+[1]Resultados!C17 -> Utilidad Neta | D18: =+D16-D17 -> 3426.7968 | E18: =+E16-E17 -> 2751.539 | F18: =+F16-F17 -> 2076.2812 | G18: =+G16-G17 -> 1401.0234 | H18: =+H16-H17 -> 1401.0234 | I18: =+I16-I17 -> 1063.3945 | J18: =+J16-J17 -> 725.7656 | K18: =+K16-K17 -> 388.1367 | ... O18: =+O16-O17 -> 4777.3124 | P18: =SUM(D18:O18) -> 26265.89
B19: 0.08 | C19: =+[1]Resultados!C18 -> Dividendos | D19: =+$B$19*D18 -> 274.14374 | E19: =+$B$19*E18 -> 220.12312 | F19: =+$B$19*F18 -> 166.1025 | G19: =+$B$19*G18 -> 112.08187 | H19: =+$B$19*H18 -> 112.08187 | I19: =+$B$19*I18 -> 85.07156 | J19: =+$B$19*J18 -> 58.061248 | K19: =+$B$19*K18 -> 31.050936 | ... O19: =+$B$19*O18 -> 382.18499 | P19: =SUM(D19:O19) -> 2101.2712
C20: =+[1]Resultados!C19 -> Utilidades Retenidas | D20: =+D18-D19 -> 3152.6531 | E20: =+E18-E19 -> 2531.4159 | F20: =+F18-F19 -> 1910.1787 | G20: =+G18-G19 -> 1288.9415 | H20: =+H18-H19 -> 1288.9415 | I20: =+I18-I19 -> 978.32294 | J20: =+J18-J19 -> 667.70435 | K20: =+K18-K19 -> 357.08576 | ... O20: =+O18-O19 -> 4395.1274 | P20: =SUM(D20:O20) -> 24164.619

Sheet Plan de Ventas y gastos 2022
C2: PROYECCIÓN DE VENTAS
E4: 44562 | F4: 44593 | G4: 44621 | H4: 44652 | I4: 44682 | J4: 44713 | K4: 44743 | L4: 44774 | M4: 44805 | N4: 44835 | O4: 44866 | P4: 44896
D5: Estacionalidad | E5: 0.12 | F5: 0.1 | G5: 0.08 | H5: 0.06 | I5: 0.06 | J5: 0.05 | K5: 0.04 | L5: 0.03 | M5: 0.08 | N5: 0.1 | O5: 0.12 | P5: 0.16 | Q5: =SUM(E5:P5) -> 1
D6: PLAN DE VENTAS
E7: 44562 | F7: 44593 | G7: 44621 | H7: 44652 | I7: 44682 | J7: 44713 | K7: 44743 | L7: 44774 | M7: 44805 | N7: 44835 | O7: 44866 | P7: 44896
D8: Ventas 2022 | E8: =+$D$9*E5 -> 27366.36 | F8: =+$D$9*F5 -> 22805.3 | G8: =+$D$9*G5 -> 18244.24 | H8: =+$D$9*H5 -> 13683.18 | I8: =+$D$9*I5 -> 13683.18 | J8: =+$D$9*J5 -> 11402.65 | K8: =+$D$9*K5 -> 9122.12 | L8: =+$D$9*L5 -> 6841.59 | ... P8: =+$D$9*P5 -> 36488.48 | Q8: =SUM(E8:P8) -> 228053
C9: Total | D9: 228053
C10: 0 | D10: Ventas modificadas | Q10: =SUM(E10:P10) -> 0
D11: =+'[1]Capital de Trabajo'!A14 -> 0
C13: 0.15 | D13: Ventas de Contado | E13: =+E8*$C$13 -> 4104.954 | F13: =+F8*$C$13 -> 3420.795 | G13: =+G8*$C$13 -> 2736.636 | H13: =+H8*$C$13 -> 2052.477 | I13: =+I8*$C$13 -> 2052.477 | J13: =+J8*$C$13 -> 1710.3975 | K13: =+K8*$C$13 -> 1368.318 | L13: =+L8*$C$13 -> 1026.2385 | ... P13: =+P8*$C$13 -> 5473.272 | Q13: =SUM(E13:P13) -> 34207.95
C14: 0.85 | D14: Ventas de Crédito | E14: =+$C$14*E8 -> 23261.406 | F14: =+$C$14*F8 -> 19384.505 | G14: =+$C$14*G8 -> 15507.604 | H14: =+$C$14*H8 -> 11630.703 | I14: =+$C$14*I8 -> 11630.703 | J14: =+$C$14*J8 -> 9692.2525 | K14: =+$C$14*K8 -> 7753.802 | L14: =+$C$14*L8 -> 5815.3515 | ... P14: =+$C$14*P8 -> 31015.208 | Q14: =SUM(E14:P14) -> 193845.05
Q15: =SUM(Q13:Q14) -> 228053
D16: Costo ventas
D17: 0.55 | E17: =+E8*$D$17 -> 15051.498 | F17: =+F8*$D$17 -> 12542.915 | G17: =+G8*$D$17 -> 10034.332 | H17: =+H8*$D$17 -> 7525.749 | I17: =+I8*$D$17 -> 7525.749 | J17: =+J8*$D$17 -> 6271.4575 | K17: =+K8*$D$17 -> 5017.166 | L17: =+L8*$D$17 -> 3762.8745 | ... P17: =+P8*$D$17 -> 20068.664 | Q17: =SUM(E17:P17) -> 125429.15
D18: Diferencia es el margen 45% | E18: =+E8-E17 -> 12314.862 | F18: =+F8-F17 -> 10262.385 | G18: =+G8-G17 -> 8209.908 | H18: =+H8-H17 -> 6157.431 | I18: =+I8-I17 -> 6157.431 | J18: =+J8-J17 -> 5131.1925 | K18: =+K8-K17 -> 4104.954 | L18: =+L8-L17 -> 3078.7155 | ... P18: =+P8-P17 -> 16419.816 | Q18: =SUM(E18:P18) -> 102623.85
Q19: =SUM(Q17:Q18) -> 228053
D20: Margen de Ganancia
D21: =100%-D17 -> 0.45 | E21: =+$D$21*E8 -> 12314.862 | F21: =+$D$21*F8 -> 10262.385 | G21: =+$D$21*G8 -> 8209.908 | H21: =+$D$21*H8 -> 6157.431 | I21: =+$D$21*I8 -> 6157.431 | J21: =+$D$21*J8 -> 5131.1925 | K21: =+$D$21*K8 -> 4104.954 | L21: =+$D$21*L8 -> 3078.7155 | ... P21: =+$D$21*P8 -> 16419.816 | Q21: =SUM(E21:P21) -> 102623.85
D24: PLAN DE GASTOS
B25: GASTOS TOTALES OPERATIVOS FINANCIEROS
B26: OBJETIVOS DE GASTO 2022
B27: GASTO OPERATIVO
B28: GASTO OPERATIVO | C28: 2022 | D28: =SUM(D29:D31) -> 72694 | E28: 0.9 | F28: REDUCCIÓN DEL 10% RESPECTO AL 2022
B29: GASTO DE VENTAS | C29: 2022 | D29: 29018 | E29: =+'[1]Base de Datos'!E28 -> 0.4 | F29: DEL GASTO OPERATIVO 2023
B30: GASTO ADMINISTRATIVO | C30: 2022 | D30: 38051 | E30: POR AJUSTE
B31: GASTO DEPRECIACIÓN | C31: 2022 | D31: 5625 | E31: IGUAL A AÑOS ANTERIORES
B33: GASTO FINANCIERO | C33: 2022 | D33: 5085 | E33: SEGÚN PLAN DE DEUDA
E35: =+E7 -> 44562 | F35: =+F7 -> 44593 | G35: =+G7 -> 44621 | H35: =+H7 -> 44652 | I35: =+I7 -> 44682 | J35: =+J7 -> 44713 | K35: =+K7 -> 44743 | L35: =+L7 -> 44774 | ... P35: =+P7 -> 44896
D36: =+[1]Resultados!C8 -> Gastos Operativos
D37: =+[1]Resultados!C9 -> Gasto Ventas | E37: =+$D$29*E5 -> 3482.16 | F37: =+$D$29*F5 -> 2901.8 | G37: =+$D$29*G5 -> 2321.44 | H37: =+$D$29*H5 -> 1741.08 | I37: =+$D$29*I5 -> 1741.08 | J37: =+$D$29*J5 -> 1450.9 | K37: =+$D$29*K5 -> 1160.72 | L37: =+$D$29*L5 -> 870.54 | ... P37: =+$D$29*P5 -> 4642.88 | Q37: =SUM(E37:P37) -> 29018
D38: =+[1]Resultados!C10 -> Gasto Administrativo | E38: =+$D$30*E5 -> 4566.12 | F38: =+$D$30*F5 -> 3805.1 | G38: =+$D$30*G5 -> 3044.08 | H38: =+$D$30*H5 -> 2283.06 | I38: =+$D$30*I5 -> 2283.06 | J38: =+$D$30*J5 -> 1902.55 | K38: =+$D$30*K5 -> 1522.04 | L38: =+$D$30*L5 -> 1141.53 | ... P38: =+$D$30*P5 -> 6088.16 | Q38: =SUM(E38:P38) -> 38051
D39: =+[1]Resultados!C11 -> Depreciaciones | E39: =+$D$31/12 -> 468.75 | F39: =+$D$31/12 -> 468.75 | G39: =+$D$31/12 -> 468.75 | H39: =+$D$31/12 -> 468.75 | I39: =+$D$31/12 -> 468.75 | J39: =+$D$31/12 -> 468.75 | K39: =+$D$31/12 -> 468.75 | L39: =+$D$31/12 -> 468.75 | ... P39: =+$D$31/12 -> 468.75 | Q39: =SUM(E39:P39) -> 5625
D40: =+[1]Resultados!C12 -> Total Gasto Operativo | E40: =SUM(E37:E39) -> 8517.03 | F40: =SUM(F37:F39) -> 7175.65 | G40: =SUM(G37:G39) -> 5834.27 | H40: =SUM(H37:H39) -> 4492.89 | I40: =SUM(I37:I39) -> 4492.89 | J40: =SUM(J37:J39) -> 3822.2 | K40: =SUM(K37:K39) -> 3151.51 | L40: =SUM(L37:L39) -> 2480.82 | ... P40: =SUM(P37:P39) -> 11199.79 | Q40: =SUM(E40:P40) -> 72694
D41: Gasto Financiero | E41: =+$D$33/12 -> 423.75 | F41: =+$D$33/12 -> 423.75 | G41: =+$D$33/12 -> 423.75 | H41: =+$D$33/12 -> 423.75 | I41: =+$D$33/12 -> 423.75 | J41: =+$D$33/12 -> 423.75 | K41: =+$D$33/12 -> 423.75 | L41: =+$D$33/12 -> 423.75 | ... P41: =+$D$33/12 -> 423.75 | Q41: =SUM(E41:P41) -> 5085
D43: Gasto Financiero | E43: 427.93968 | F43: 427.19624 | G43: 426.44536 | H43: 425.68698 | I43: 424.92102 | J43: 424.14739 | K43: 423.36603 | L43: 422.57685 | M43: 421.77979 | N43: 420.97475 | O43: 420.16166 | P43: 419.34044 | Q43: =SUM(E43:P43) -> 5084.5362

Sheet Resultados proyectados 2022
C2: ESTADOS RESULTADOS PROYECTADOS 2023
D3: 44562 | E3: 44593 | F3: 44621 | G3: 44652 | H3: 44682 | I3: 44713 | J3: 44743 | K3: 44774 | L3: 44805 | M3: 44835 | N3: 44866 | O3: 44896 | P3: TOTAL
C4: Ventas | D4: =+'Plan de Ventas y gastos 2022'!E8 -> 27366.36 | E4: =+'Plan de Ventas y gastos 2022'!F8 -> 22805.3 | F4: =+'Plan de Ventas y gastos 2022'!G8 -> 18244.24 | G4: =+'Plan de Ventas y gastos 2022'!H8 -> 13683.18 | H4: =+'Plan de Ventas y gastos 2022'!I8 -> 13683.18 | I4: =+'Plan de Ventas y gastos 2022'!J8 -> 11402.65 | J4: =+'Plan de Ventas y gastos 2022'!K8 -> 9122.12 | K4: =+'Plan de Ventas y gastos 2022'!L8 -> 6841.59 | ... O4: =+'Plan de Ventas y gastos 2022'!P8 -> 36488.48 | P4: =SUM(D4:O4) -> 228053
C5: Costo ventas | D5: =+'Plan de Ventas y gastos 2022'!E17 -> 15051.498 | E5: =+'Plan de Ventas y gastos 2022'!F17 -> 12542.915 | F5: =+'Plan de Ventas y gastos 2022'!G17 -> 10034.332 | G5: =+'Plan de Ventas y gastos 2022'!H17 -> 7525.749 | H5: =+'Plan de Ventas y gastos 2022'!I17 -> 7525.749 | I5: =+'Plan de Ventas y gastos 2022'!J17 -> 6271.4575 | J5: =+'Plan de Ventas y gastos 2022'!K17 -> 5017.166 | K5: =+'Plan de Ventas y gastos 2022'!L17 -> 3762.8745 | ... O5: =+'Plan de Ventas y gastos 2022'!P17 -> 20068.664 | P5: =SUM(D5:O5) -> 125429.15
C6: Margen de Ganancia | D6: =+'Plan de Ventas y gastos 2022'!E21 -> 12314.862 | E6: =+'Plan de Ventas y gastos 2022'!F21 -> 10262.385 | F6: =+'Plan de Ventas y gastos 2022'!G21 -> 8209.908 | G6: =+'Plan de Ventas y gastos 2022'!H21 -> 6157.431 | H6: =+'Plan de Ventas y gastos 2022'!I21 -> 6157.431 | I6: =+'Plan de Ventas y gastos 2022'!J21 -> 5131.1925 | J6: =+'Plan de Ventas y gastos 2022'!K21 -> 4104.954 | K6: =+'Plan de Ventas y gastos 2022'!L21 -> 3078.7155 | ... O6: =+'Plan de Ventas y gastos 2022'!P21 -> 16419.816 | P6: =SUM(D6:O6) -> 102623.85 | Q6: =+P5+P6 -> 228053
C7: Margen de Ganancia % | D7: 0.45 | E7: 0.45 | F7: 0.45 | G7: 0.45 | H7: 0.45 | I7: 0.45 | J7: 0.45 | K7: 0.45 | L7: 0.45 | M7: 0.45 | N7: 0.45 | O7: 0.45
B9: 1 | C9: =+[1]Resultados!C8 -> Gastos Operativos | Q9: CONTROL
B10: a | C10: =+[1]Resultados!C9 -> Gasto Ventas | D10: =+'Plan de Ventas y gastos 2022'!E37 -> 3482.16 | E10: =+'Plan de Ventas y gastos 2022'!F37 -> 2901.8 | F10: =+'Plan de Ventas y gastos 2022'!G37 -> 2321.44 | G10: =+'Plan de Ventas y gastos 2022'!H37 -> 1741.08 | H10: =+'Plan de Ventas y gastos 2022'!I37 -> 1741.08 | I10: =+'Plan de Ventas y gastos 2022'!J37 -> 1450.9 | J10: =+'Plan de Ventas y gastos 2022'!K37 -> 1160.72 | K10: =+'Plan de Ventas y gastos 2022'!L37 -> 870.54 | ... O10: =+'Plan de Ventas y gastos 2022'!P37 -> 4642.88 | P10: =SUM(D10:O10) -> 29018 | Q10: =+'Plan de Ventas y gastos 2023'!D29 -> 29018
B11: b | C11: =+[1]Resultados!C10 -> Gasto Administrativo | D11: =+'Plan de Ventas y gastos 2022'!E38 -> 4566.12 | E11: =+'Plan de Ventas y gastos 2022'!F38 -> 3805.1 | F11: =+'Plan de Ventas y gastos 2022'!G38 -> 3044.08 | G11: =+'Plan de Ventas y gastos 2022'!H38 -> 2283.06 | H11: =+'Plan de Ventas y gastos 2022'!I38 -> 2283.06 | I11: =+'Plan de Ventas y gastos 2022'!J38 -> 1902.55 | J11: =+'Plan de Ventas y gastos 2022'!K38 -> 1522.04 | K11: =+'Plan de Ventas y gastos 2022'!L38 -> 1141.53 | ... O11: =+'Plan de Ventas y gastos 2022'!P38 -> 6088.16 | P11: =SUM(D11:O11) -> 38051 | Q11: =+'Plan de Ventas y gastos 2023'!D30 -> 38051
B12: c | C12: =+[1]Resultados!C11 -> Depreciaciones | D12: =+'Plan de Ventas y gastos 2022'!E39 -> 468.75 | E12: =+'Plan de Ventas y gastos 2022'!F39 -> 468.75 | F12: =+'Plan de Ventas y gastos 2022'!G39 -> 468.75 | G12: =+'Plan de Ventas y gastos 2022'!H39 -> 468.75 | H12: =+'Plan de Ventas y gastos 2022'!I39 -> 468.75 | I12: =+'Plan de Ventas y gastos 2022'!J39 -> 468.75 | J12: =+'Plan de Ventas y gastos 2022'!K39 -> 468.75 | K12: =+'Plan de Ventas y gastos 2022'!L39 -> 468.75 | ... O12: =+'Plan de Ventas y gastos 2022'!P39 -> 468.75 | P12: =SUM(D12:O12) -> 5625 | Q12: =+'Plan de Ventas y gastos 2023'!D31 -> 5625
C13: =+[1]Resultados!C12 -> Total Gasto Operativo | D13: =SUM(D10:D12) -> 8517.03 | E13: =SUM(E10:E12) -> 7175.65 | F13: =SUM(F10:F12) -> 5834.27 | G13: =SUM(G10:G12) -> 4492.89 | H13: =SUM(H10:H12) -> 4492.89 | I13: =SUM(I10:I12) -> 3822.2 | J13: =SUM(J10:J12) -> 3151.51 | K13: =SUM(K10:K12) -> 2480.82 | ... P13: =SUM(P10:P12) -> 72694 | Q13: =+'Plan de Ventas y gastos 2023'!D28 -> 72694
B14: UAII | C14: =+[1]Resultados!C13 -> Utlidades Operativas | D14: =+D6-D13 -> 3797.832 | E14: =+E6-E13 -> 3086.735 | F14: =+F6-F13 -> 2375.638 | G14: =+G6-G13 -> 1664.541 | H14: =+H6-H13 -> 1664.541 | I14: =+I6-I13 -> 1308.9925 | J14: =+J6-J13 -> 953.444 | K14: =+K6-K13 -> 597.8955 | ... O14: =+O6-O13 -> 5220.026
B15: 2 | C15: =+[1]Resultados!C14 -> Gasto Financiero | D15: =+'Plan de Ventas y gastos 2022'!E41 -> 423.75 | E15: =+'Plan de Ventas y gastos 2022'!F41 -> 423.75 | F15: =+'Plan de Ventas y gastos 2022'!G41 -> 423.75 | G15: =+'Plan de Ventas y gastos 2022'!H41 -> 423.75 | H15: =+'Plan de Ventas y gastos 2022'!I41 -> 423.75 | I15: =+'Plan de Ventas y gastos 2022'!J41 -> 423.75 | J15: =+'Plan de Ventas y gastos 2022'!K41 -> 423.75 | K15: =+'Plan de Ventas y gastos 2022'!L41 -> 423.75 | ... O15: =+'Plan de Ventas y gastos 2022'!P41 -> 423.75 | P15: =SUM(D15:O15) -> 5085 | Q15: =+'Plan de Ventas y gastos 2023'!D33 -> 5085
B16: UAII | C16: =+[1]Resultados!C15 -> Utilidad antes de Impuestos | D16: =+D14-D15 -> 3374.082 | E16: =+E14-E15 -> 2662.985 | F16: =+F14-F15 -> 1951.888 | G16: =+G14-G15 -> 1240.791 | H16: =+H14-H15 -> 1240.791 | I16: =+I14-I15 -> 885.2425 | J16: =+J14-J15 -> 529.694 | K16: =+K14-K15 -> 174.1455 | ... O16: =+O14-O15 -> 4796.276 | P16: =SUM(D16:O16) -> 24844.85
B17: 0.3 | C17: =+[1]Resultados!C16 -> Impuestos Renta | D17: =+$B$17*D16 -> 1012.2246 | E17: =+$B$17*E16 -> 798.8955 | F17: =+$B$17*F16 -> 585.5664 | G17: =+$B$17*G16 -> 372.2373 | H17: =+$B$17*H16 -> 372.2373 | I17: =+$B$17*I16 -> 265.57275 | J17: =+$B$17*J16 -> 158.9082 | K17: =+$B$17*K16 -> 52.24365 | ... O17: =+$B$17*O16 -> 1438.8828 | P17: =SUM(D17:O17) -> 7453.455
C18: =+[1]Resultados!C17 -> Utilidad Neta | D18: =+D16-D17 -> 2361.8574 | E18: =+E16-E17 -> 1864.0895 | F18: =+F16-F17 -> 1366.3216 | G18: =+G16-G17 -> 868.5537 | H18: =+H16-H17 -> 868.5537 | I18: =+I16-I17 -> 619.66975 | J18: =+J16-J17 -> 370.7858 | K18: =+K16-K17 -> 121.90185 | ... O18: =+O16-O17 -> 3357.3932 | P18: =SUM(D18:O18) -> 17391.395
B19: 0.08 | C19: =+[1]Resultados!C18 -> Dividendos | D19: =+$B$19*D18 -> 188.94859 | E19: =+$B$19*E18 -> 149.12716 | F19: =+$B$19*F18 -> 109.30573 | G19: =+$B$19*G18 -> 69.484296 | H19: =+$B$19*H18 -> 69.484296 | I19: =+$B$19*I18 -> 49.57358 | J19: =+$B$19*J18 -> 29.662864 | K19: =+$B$19*K18 -> 9.752148 | ... O19: =+$B$19*O18 -> 268.59146 | P19: =SUM(D19:O19) -> 1391.3116
C20: =+[1]Resultados!C19 -> Utilidades Retenidas | D20: =+D18-D19 -> 2172.9088 | E20: =+E18-E19 -> 1714.9623 | F20: =+F18-F19 -> 1257.0159 | G20: =+G18-G19 -> 799.0694 | H20: =+H18-H19 -> 799.0694 | I20: =+I18-I19 -> 570.09617 | J20: =+J18-J19 -> 341.12294 | K20: =+K18-K19 -> 112.1497 | ... O20: =+O18-O19 -> 3088.8017 | P20: =SUM(D20:O20) -> 16000.083

Sheet Plan de Ventas y gastos DUPLICA
C2: PROYECCIÓN DE VENTAS
E4: 44562 | F4: 44593 | G4: 44621 | H4: 44652 | I4: 44682 | J4: 44713 | K4: 44743 | L4: 44774 | M4: 44805 | N4: 44835 | O4: 44866 | P4: 44896
D5: Estacionalidad | E5: 0.12 | F5: 0.1 | G5: 0.08 | H5: 0.06 | I5: 0.06 | J5: 0.05 | K5: 0.04 | L5: 0.03 | M5: 0.08 | N5: 0.1 | O5: 0.12 | P5: 0.16 | Q5: =SUM(E5:P5) -> 1
D6: PLAN DE VENTAS
E7: 44562 | F7: 44593 | G7: 44621 | H7: 44652 | I7: 44682 | J7: 44713 | K7: 44743 | L7: 44774 | M7: 44805 | N7: 44835 | O7: 44866 | P7: 44896
D8: Ventas 2022 | E8: =+$D$9*E5 -> 27366.36 | F8: =+$D$9*F5 -> 22805.3 | G8: =+$D$9*G5 -> 18244.24 | H8: =+$D$9*H5 -> 13683.18 | I8: =+$D$9*I5 -> 13683.18 | J8: =+$D$9*J5 -> 11402.65 | K8: =+$D$9*K5 -> 9122.12 | L8: =+$D$9*L5 -> 6841.59 | ... P8: =+$D$9*P5 -> 36488.48 | Q8: =SUM(E8:P8) -> 228053
C9: Total | D9: 228053
C10: 0 | D10: Ventas modificadas | Q10: =SUM(E10:P10) -> 0
D11: =+'[1]Capital de Trabajo'!A14 -> 0
C13: 0.15 | D13: Ventas de Contado | E13: =+$C$13*E8 -> 4104.954 | F13: =+$C$13*F8 -> 3420.795 | G13: =+$C$13*G8 -> 2736.636 | H13: =+$C$13*H8 -> 2052.477 | I13: =+$C$13*I8 -> 2052.477 | J13: =+$C$13*J8 -> 1710.3975 | K13: =+$C$13*K8 -> 1368.318 | L13: =+$C$13*L8 -> 1026.2385 | ... P13: =+$C$13*P8 -> 5473.272 | Q13: =SUM(E13:P13) -> 34207.95
C14: 0.85 | D14: Ventas de Crédito | E14: =+$C$14*E8 -> 23261.406 | F14: =+$C$14*F8 -> 19384.505 | G14: =+$C$14*G8 -> 15507.604 | H14: =+$C$14*H8 -> 11630.703 | I14: =+$C$14*I8 -> 11630.703 | J14: =+$C$14*J8 -> 9692.2525 | K14: =+$C$14*K8 -> 7753.802 | L14: =+$C$14*L8 -> 5815.3515 | ... P14: =+$C$14*P8 -> 31015.208 | Q14: =SUM(E14:P14) -> 193845.05
Q15: =SUM(Q13:Q14) -> 228053
D16: Costo ventas
D17: 0.55 | E17: =+$D$17*E8 -> 15051.498 | F17: =+$D$17*F8 -> 12542.915 | G17: =+$D$17*G8 -> 10034.332 | H17: =+$D$17*H8 -> 7525.749 | I17: =+$D$17*I8 -> 7525.749 | J17: =+$D$17*J8 -> 6271.4575 | K17: =+$D$17*K8 -> 5017.166 | L17: =+$D$17*L8 -> 3762.8745 | ... P17: =+$D$17*P8 -> 20068.664 | Q17: =SUM(E17:P17) -> 125429.15
D18: Diferencia es el margen 45% | E18: =+E8-E17 -> 12314.862 | F18: =+F8-F17 -> 10262.385 | G18: =+G8-G17 -> 8209.908 | H18: =+H8-H17 -> 6157.431 | I18: =+I8-I17 -> 6157.431 | J18: =+J8-J17 -> 5131.1925 | K18: =+K8-K17 -> 4104.954 | L18: =+L8-L17 -> 3078.7155 | ... P18: =+P8-P17 -> 16419.816 | Q18: =SUM(E18:P18) -> 102623.85
Q19: =SUM(Q17:Q18) -> 228053
D20: Margen de Ganancia
D21: =100%-D17 -> 0.45 | E21: =+$D$21*E8 -> 12314.862 | F21: =+$D$21*F8 -> 10262.385 | G21: =+$D$21*G8 -> 8209.908 | H21: =+$D$21*H8 -> 6157.431 | I21: =+$D$21*I8 -> 6157.431 | J21: =+$D$21*J8 -> 5131.1925 | K21: =+$D$21*K8 -> 4104.954 | L21: =+$D$21*L8 -> 3078.7155 | ... P21: =+$D$21*P8 -> 16419.816 | Q21: =SUM(E21:P21) -> 102623.85
D24: PLAN DE GASTOS
B25: GASTOS TOTALES OPERATIVOS FINANCIEROS
B26: OBJETIVOS DE GASTO 2022
B27: GASTO OPERATIVO | C27: 2022
B28: GASTO OPERATIVO | C28: 2022 | D28: =SUM(D29:D31) -> 72694 | E28: 0.9 | F28: REDUCCIÓN DEL 10% RESPECTO AL 2022
B29: GASTO DE VENTAS | C29: 2022 | D29: 29018 | E29: =+'[1]Base de Datos'!E28 -> 0.4 | F29: DEL GASTO OPERATIVO 2023
B30: GASTO ADMINISTRATIVO | C30: 2022 | D30: 38051 | E30: POR AJUSTE
B31: GASTO DEPRECIACIÓN | C31: 2022 | D31: 5625 | E31: IGUAL A AÑOS ANTERIORES
B33: GASTO FINANCIERO | C33: 2022 | D33: 5085 | E33: SEGÚN PLAN DE DEUDA
E35: =+E7 -> 44562 | F35: =+F7 -> 44593 | G35: =+G7 -> 44621 | H35: =+H7 -> 44652 | I35: =+I7 -> 44682 | J35: =+J7 -> 44713 | K35: =+K7 -> 44743 | L35: =+L7 -> 44774 | ... P35: =+P7 -> 44896
D36: =+[1]Resultados!C8 -> Gastos Operativos
D37: =+[1]Resultados!C9 -> Gasto Ventas | E37: =+$D$29*E5 -> 3482.16 | F37: =+$D$29*F5 -> 2901.8 | G37: =+$D$29*G5 -> 2321.44 | H37: =+$D$29*H5 -> 1741.08 | I37: =+$D$29*I5 -> 1741.08 | J37: =+$D$29*J5 -> 1450.9 | K37: =+$D$29*K5 -> 1160.72 | L37: =+$D$29*L5 -> 870.54 | ... P37: =+$D$29*P5 -> 4642.88 | Q37: =SUM(E37:P37) -> 29018
D38: =+[1]Resultados!C10 -> Gasto Administrativo | E38: =+$D$30*E5 -> 4566.12 | F38: =+$D$30*F5 -> 3805.1 | G38: =+$D$30*G5 -> 3044.08 | H38: =+$D$30*H5 -> 2283.06 | I38: =+$D$30*I5 -> 2283.06 | J38: =+$D$30*J5 -> 1902.55 | K38: =+$D$30*K5 -> 1522.04 | L38: =+$D$30*L5 -> 1141.53 | ... P38: =+$D$30*P5 -> 6088.16 | Q38: =SUM(E38:P38) -> 38051
D39: =+[1]Resultados!C11 -> Depreciaciones | E39: =+$D$31/12 -> 468.75 | F39: =+$D$31/12 -> 468.75 | G39: =+$D$31/12 -> 468.75 | H39: =+$D$31/12 -> 468.75 | I39: =+$D$31/12 -> 468.75 | J39: =+$D$31/12 -> 468.75 | K39: =+$D$31/12 -> 468.75 | L39: =+$D$31/12 -> 468.75 | ... P39: =+$D$31/12 -> 468.75 | Q39: =SUM(E39:P39) -> 5625
D40: =+[1]Resultados!C12 -> Total Gasto Operativo | E40: =SUM(E37:E39) -> 8517.03 | F40: =SUM(F37:F39) -> 7175.65 | G40: =SUM(G37:G39) -> 5834.27 | H40: =SUM(H37:H39) -> 4492.89 | I40: =SUM(I37:I39) -> 4492.89 | J40: =SUM(J37:J39) -> 3822.2 | K40: =SUM(K37:K39) -> 3151.51 | L40: =SUM(L37:L39) -> 2480.82 | ... P40: =SUM(P37:P39) -> 11199.79 | Q40: =SUM(E40:P40) -> 72694
D41: Gasto Financiero | E41: =+$D$33/12 -> 423.75 | F41: =+$D$33/12 -> 423.75 | G41: =+$D$33/12 -> 423.75 | H41: =+$D$33/12 -> 423.75 | I41: =+$D$33/12 -> 423.75 | J41: =+$D$33/12 -> 423.75 | K41: =+$D$33/12 -> 423.75 | L41: =+$D$33/12 -> 423.75 | ... P41: =+$D$33/12 -> 423.75 | Q41: =SUM(E41:P41) -> 5085
D43: Gasto Financiero | E43: 427.93968 | F43: 427.19624 | G43: 426.44536 | H43: 425.68698 | I43: 424.92102 | J43: 424.14739 | K43: 423.36603 | L43: 422.57685 | M43: 421.77979 | N43: 420.97475 | O43: 420.16166 | P43: 419.34044 | Q43: =SUM(E43:P43) -> 5084.5362
